vectordb/__init__.py
vectordb/chunking.py
vectordb/embedding.py
vectordb/memory.py
vectordb/storage.py
vectordb/vector_search.py
vectordb2-0.1.9.dist-info/LICENSE
vectordb2-0.1.9.dist-info/METADATA
vectordb2-0.1.9.dist-info/WHEEL
vectordb2-0.1.9.dist-info/top_level.txt
vectordb2-0.1.9.dist-info/RECORD
