Metadata-Version: 2.1
Name: vectordb2
Version: 0.1.9
Summary: A lightweight Python package for storing and retrieving text using chunking, embedding, and vector search
Home-page: https://github.com/kagisearch/vectordb
Author: Vladimir Prelovac
Author-email: vlad@kagi.com
Keywords: text chunking embedding vector search
Classifier: Development Status :: 3 - Alpha
Classifier: Intended Audience :: Developers
Classifier: License :: OSI Approved :: MIT License
Classifier: Programming Language :: Python :: 3
Classifier: Programming Language :: Python :: 3.6
Classifier: Programming Language :: Python :: 3.7
Classifier: Programming Language :: Python :: 3.8
Classifier: Programming Language :: Python :: 3.9
Classifier: Programming Language :: Python :: 3.10
Classifier: Programming Language :: Python :: 3.11
License-File: LICENSE
Requires-Dist: torch >=1.9.0
Requires-Dist: transformers >=4.10.0
Requires-Dist: numpy >=1.21.0
Requires-Dist: scikit-learn >=0.24.0
Requires-Dist: scipy >=1.7.0
Requires-Dist: sentence-transformers
Requires-Dist: faiss-cpu
Requires-Dist: tensorflow-text
